FAIRsoft/__init__.py
FAIRsoft/utils.py
FAIRsoft/importers/setup.py
FAIRsoft/importers/bioconda_biotools_galaxy_imp/cli.py
FAIRsoft/importers/bioconda_biotools_galaxy_imp/main.py
FAIRsoft/importers/bioconda_biotools_galaxy_imp/utils.py
FAIRsoft/importers/bioconda_imp/cli.py
FAIRsoft/importers/bioconda_imp/main.py
FAIRsoft/importers/bioconda_imp/utils.py
FAIRsoft/importers/bioconductor_imp/cli.py
FAIRsoft/importers/opeb_metrics_imp/cli.py
FAIRsoft/importers/opeb_metrics_imp/import_from_file.py
FAIRsoft/importers/opeb_metrics_imp/main.py
FAIRsoft/importers/opeb_metrics_imp/utils.py
FAIRsoft/importers/repositories_imp/cli.py
FAIRsoft/importers/repositories_imp/importfrom_opeb.py
FAIRsoft/importers/repositories_imp/main.py
FAIRsoft/importers/repositories_imp/plus_enricher.py
FAIRsoft/importers/sourceforge_imp/cli.py
FAIRsoft/importers/sourceforge_imp/main.py
FAIRsoft/importers/sourceforge_imp/utils.py
FAIRsoft/importers/toolshed_imp/cli.py
FAIRsoft/importers/toolshed_imp/galaxy_metadata.py
FAIRsoft/importers/toolshed_imp/load_from_json.py
FAIRsoft/importers/toolshed_imp/main.py
FAIRsoft/importers/toolshed_imp/repos_config_importer.py
FAIRsoft/importers/toolshed_imp/repos_metadata_importer.py
FAIRsoft/importers/toolshed_imp/utils.py
FAIRsoft/indicators_evaluation/FAIR_indicators_eval.py
FAIRsoft/indicators_evaluation/__init__.py
FAIRsoft/integration/cli.py
FAIRsoft/integration/integration.py
FAIRsoft/integration/run_integration.py
FAIRsoft/transformation/cli.py
FAIRsoft/transformation/meta_transformers.py
FAIRsoft/transformation/transform_raw.py
FAIRsoft-0.2.1.dist-info/LICENSE
FAIRsoft-0.2.1.dist-info/METADATA
FAIRsoft-0.2.1.dist-info/WHEEL
FAIRsoft-0.2.1.dist-info/entry_points.txt
FAIRsoft-0.2.1.dist-info/top_level.txt
FAIRsoft-0.2.1.dist-info/RECORD
