Metadata-Version: 2.1
Name: FAIRsoft
Version: 0.2.1
Summary: FAIRsoft package for the aggregation of Life Sciences software metadata and FAIR evaluation.
Home-page: https://gitlab.bsc.es/inb/elixir/software-observatory/FAIRsoft_ETL/-/tree/master/FAIRsoft
Author: Eva Martin del Pico
Author-email: Eva Martin del Pico <eva.martin@bsc.es>
License: AGLP-3.0
Project-URL: Bug Tracker, https://gitlab.bsc.es/inb/elixir/software-observatory/FAIRsoft_ETL/issues
Project-URL: Repository, https://gitlab.bsc.es/inb/elixir/software-observatory/FAIRsoft_ETL/-/tree/master/FAIRsoft
Classifier: Development Status :: 4 - Beta
Classifier: License :: OSI Approved :: GNU Affero General Public License v3
Requires-Python: >=3.7
License-File: LICENSE
Requires-Dist: bidict
Requires-Dist: matplotlib
Requires-Dist: munch
Requires-Dist: pymongo
Requires-Dist: requests
Requires-Dist: selenium
Requires-Dist: simplejson
Requires-Dist: webdriver-manager
